laklak/__init__.py
laklak/core.py
laklak/exchanges.py
laklak-1.0.9.dist-info/licenses/LICENSE
modules/__init__.py
modules/influx_writer.py
modules/exchanges/__init__.py
modules/exchanges/bybit.py
modules/exchanges/deribit.py
modules/exchanges/yfinance.py
laklak-1.0.9.dist-info/METADATA
laklak-1.0.9.dist-info/WHEEL
laklak-1.0.9.dist-info/entry_points.txt
laklak-1.0.9.dist-info/top_level.txt
laklak-1.0.9.dist-info/RECORD
