Metadata-Version: 2.4
Name: laklak
Version: 1.0.9
Summary: Cross-Platform Market Data Collector
Home-page: https://github.com/Eulex0x/laklak
Author: Eulex0x
Author-email: Eulex0x <milad@safda.de>
License: MIT
Project-URL: Homepage, https://github.com/Eulex0x/laklak
Project-URL: Documentation, https://github.com/Eulex0x/laklak/tree/main/Info
Project-URL: Repository, https://github.com/Eulex0x/laklak
Project-URL: Bug Reports, https://github.com/Eulex0x/laklak/issues
Keywords: trading,finance,data,crypto,stocks,forex,bybit,deribit,yfinance,influxdb,market-data
Classifier: Development Status :: 4 - Beta
Classifier: Intended Audience :: Developers
Classifier: Intended Audience :: Financial and Insurance Industry
Classifier: Topic :: Office/Business :: Financial :: Investment
Classifier: License :: OSI Approved :: MIT License
Classifier: Programming Language :: Python :: 3
Classifier: Programming Language :: Python :: 3.7
Classifier: Programming Language :: Python :: 3.8
Classifier: Programming Language :: Python :: 3.9
Classifier: Programming Language :: Python :: 3.10
Classifier: Programming Language :: Python :: 3.11
Classifier: Programming Language :: Python :: 3.12
Requires-Python: >=3.7
License-File: LICENSE
Requires-Dist: requests
Requires-Dist: python-dotenv
Requires-Dist: pandas
Requires-Dist: influxdb-client
Requires-Dist: influxdb
Requires-Dist: yfinance
Provides-Extra: dev
Requires-Dist: pytest>=7.0; extra == "dev"
Requires-Dist: pytest-cov>=4.0; extra == "dev"
Requires-Dist: black>=22.0; extra == "dev"
Requires-Dist: flake8>=5.0; extra == "dev"
Requires-Dist: mypy>=0.990; extra == "dev"
Dynamic: author
Dynamic: home-page
Dynamic: license-file
Dynamic: requires-python
